Metadata-Version: 2.0
Name: drf-autodocs
Version: 0.4.3
Summary: Extensible auto django rest framework api generator
Home-page: https://github.com/iMakedonsky/drf-autodocs
Author: Mashianov Oleksander
Author-email: mashianov@gmail.com
License: BSD
Platform: UNKNOWN
Classifier: Development Status :: 5 - Production/Stable
Classifier: Environment :: Web Environment
Classifier: Framework :: Django
Classifier: Intended Audience :: Developers
Classifier: License :: OSI Approved :: BSD License
Classifier: Operating System :: OS Independent
Classifier: Programming Language :: Python
Classifier: Programming Language :: Python :: 3
Classifier: Programming Language :: Python :: 3.4
Classifier: Programming Language :: Python :: 3.5
Requires-Dist: addict (>=2.0.0)
Requires-Dist: django (>=1.8)
Requires-Dist: djangorestframework (>=3)
Requires-Dist: markdown (>=2.6.7)
